{
  "id": "plan_20260220_164949_1089",
  "summary": "收集2026年2月20日热点信息并总结成文章",
  "status": "completed",
  "created_at": "2026-02-20 16:49:49",
  "steps": [
    {
      "id": "step_1",
      "description": "搜索今日热点相关信息",
      "status": "completed",
      "result": "已收集到2026年2月20日热点：横琴口岸客流、港珠澳大桥车流、春节档票房、米兰冬奥会宁忠岩夺冠、湖南消防员牺牲、谭凯回应没戏拍、辽宁男篮引进外援、大衣哥女儿回娘家、李家诚控告周秀娜等"
    },
    {
      "id": "step_2",
      "description": "整理分类热点内容（体育、娱乐、社会、国际等）",
      "status": "completed",
      "result": "分类完成：【体育】米兰冬奥会宁忠岩破纪录夺冠、辽宁男篮引进外援；【社会】横琴口岸客流超47.7万、港珠澳大桥车流创新高、湖南消防员牺牲；【娱乐】春节档票房32亿、谭凯回应没戏拍、大衣哥女儿回娘家、李家诚控告周秀娜"
    },
    {
      "id": "step_3",
      "description": "撰写热点总结文章",
      "status": "completed",
      "result": "文章已撰写完成并保存到 ./热点汇总_20260220.md"
    },
    {
      "id": "step_4",
      "description": "保存文章到本地文件",
      "status": "completed",
      "result": "文章已成功保存到 ./热点汇总_20260220.md"
    }
  ]
}